gui_runner/__init__.py
gui_runner/config_manager.py
gui_runner/gui_main.py
gui_runner/gui_subwindow.py
gui_runner/main.py
gui_runner/tooltip.py
gui_runner/ui_dict.py
gui_runner/utils.py
gui_runner-0.1.1.dist-info/licenses/LICENSE
gui_runner-0.1.1.dist-info/METADATA
gui_runner-0.1.1.dist-info/WHEEL
gui_runner-0.1.1.dist-info/entry_points.txt
gui_runner-0.1.1.dist-info/top_level.txt
gui_runner-0.1.1.dist-info/RECORD
