Metadata-Version: 2.4
Name: gui-runner
Version: 0.1.1
Summary: Configurable GUI runner for Python/Node.js scripts
Home-page: https://github.com/985ch/gui-runner
Author: 985ch
Classifier: Programming Language :: Python :: 3
Classifier: License :: OSI Approved :: MIT License
Classifier: Operating System :: OS Independent
Requires-Python: >=3.6
License-File: LICENSE
Dynamic: author
Dynamic: classifier
Dynamic: description
Dynamic: description-content-type
Dynamic: home-page
Dynamic: license-file
Dynamic: requires-python
Dynamic: summary
